nixconverter/__init__.py
nixconverter/__main__.py
nixconverter/eegbase_nix_converter.py
nixconverter/brainvisionconverter/__init__.py
nixconverter/brainvisionconverter/brainvision_mapping.json
nixconverter/brainvisionconverter/converter.py
nixconverter/odmlconverter/__init__.py
nixconverter/odmlconverter/converter.py
nixconverter/odmlconverter/mapper.py
nixconverter/odmlconverter/mapping_generator.py
nixconverter/odmlconverter/odml_mapping.json
nixconverter/utils/__init__.py
nixconverter/utils/conf.py
nixconverter/utils/utils.py
tests/__init__.py
tests/test_brainvision_converter.py
tests/test_converter_utils.py
tests/test_eegbase_nix_converter.py
tests/test_odml_mapper.py
tests/test_odml_mapping_generator.py
tests/data/eegbase/Experiment_P3_Numbers/metadata.xml
tests/data/eegbase/Experiment_P3_Numbers/Data/P3Numbers_20150618_f_11_001.eeg
tests/data/eegbase/Experiment_P3_Numbers/Data/P3Numbers_20150618_f_11_001.txt
tests/data/eegbase/Experiment_P3_Numbers/Data/P3Numbers_20150618_f_11_001.vhdr
tests/data/eegbase/Experiment_P3_Numbers/Data/P3Numbers_20150618_f_11_001.vmrk
tests/data/eegbase/Experiment_P3_Numbers/Scenario/numbers.zip
tests/data/odml/odml_test_data.py
tests/data/odml/odml_test_mapping.json
tests/data/odml/__pycache__/odml_test_data.cpython-38.pyc
eegbase_nix_converter-1.0.4.dist-info/LICENSE
eegbase_nix_converter-1.0.4.dist-info/METADATA
eegbase_nix_converter-1.0.4.dist-info/WHEEL
eegbase_nix_converter-1.0.4.dist-info/top_level.txt
eegbase_nix_converter-1.0.4.dist-info/RECORD
