Metadata-Version: 2.1
Name: eegbase-nix-converter
Version: 1.0.4
Summary: EEGbase -> NIX converter converts BranVision/odML dataset to a NIX container file
Home-page: https://gitlab.com/honza.seda/eegbase-nix-converter
Author: Jan Sedivy
Author-email: honza.seeda@gmail.com
License: UNKNOWN
Platform: UNKNOWN
Classifier: Programming Language :: Python :: 3
Classifier: License :: OSI Approved :: GNU Lesser General Public License v3 (LGPLv3)
Classifier: Operating System :: OS Independent
Requires-Python: >=3.8
Requires-Dist: numpy (~=1.18.1)
Requires-Dist: odML (~=1.4.5)
Requires-Dist: nixodmlconverter (~=0.0.7)
Requires-Dist: mne (==0.20.3)
Requires-Dist: nixio (~=1.5.0b4)
Requires-Dist: docopt (~=0.6.2)
